mynodesdk/__init__.py
mynodesdk/main.py
mynodesdk/util.py
mynodesdk-0.0.4.dist-info/LICENSE
mynodesdk-0.0.4.dist-info/METADATA
mynodesdk-0.0.4.dist-info/WHEEL
mynodesdk-0.0.4.dist-info/entry_points.txt
mynodesdk-0.0.4.dist-info/top_level.txt
mynodesdk-0.0.4.dist-info/RECORD
